pydigits/__init__.py
py_digits-1.0.2.dist-info/LICENSE
py_digits-1.0.2.dist-info/METADATA
py_digits-1.0.2.dist-info/WHEEL
py_digits-1.0.2.dist-info/top_level.txt
py_digits-1.0.2.dist-info/RECORD
