Metadata-Version: 2.1
Name: py-digits
Version: 1.0.2
Summary: Add the first X Pi digits
Home-page: https://github.com/Baelfire18/py-digits
Author: Jose Antonio Castro
Author-email: jacastro18@uc.cl
License: MIT
Keywords: pi,sum,CAPTCHA,robot,binary
Platform: UNKNOWN
License-File: LICENSE
Requires-Dist: mpmath (==1.2.1)
Requires-Dist: typing-extensions (==4.1.1)
